<?xml version="1.0" encoding="UTF-8"?>
<!DOCTYPE hibernate-reverse-engineering PUBLIC "-//Hibernate/Hibernate Reverse Engineering DTD 3.0//EN" "http://hibernate.org/dtd/hibernate-reverse-engineering-3.0.dtd" >

<hibernate-reverse-engineering>
  <table-filter match-schema="dodo" match-name=".*"/>
  <table-filter match-catalog="dodo" match-name="category"/>
  <table-filter match-catalog="dodo" match-name="invoice"/>
  <table-filter match-catalog="dodo" match-name="item"/>
  <table-filter match-catalog="dodo" match-name="notification"/>
  <table-filter match-catalog="dodo" match-name="order"/>
  <table-filter match-catalog="dodo" match-name="ordercancellation"/>
  <table-filter match-catalog="dodo" match-name="orderdetail"/>
  <table-filter match-catalog="dodo" match-name="orderstatus"/>
  <table-filter match-catalog="dodo" match-name="parentcategory"/>
  <table-filter match-catalog="dodo" match-name="paymentinfo"/>
  <table-filter match-catalog="dodo" match-name="product"/>
  <table-filter match-catalog="dodo" match-name="productattribute"/>
  <table-filter match-catalog="dodo" match-name="promotion"/>
  <table-filter match-catalog="dodo" match-name="review"/>
  <table-filter match-catalog="dodo" match-name="role"/>
  <table-filter match-catalog="dodo" match-name="salesdata"/>
  <table-filter match-catalog="dodo" match-name="shopowner"/>
  <table-filter match-catalog="dodo" match-name="shopownercoupon"/>
  <table-filter match-catalog="dodo" match-name="transaction"/>
  <table-filter match-catalog="dodo" match-name="user"/>
  <table-filter match-catalog="dodo" match-name="wishlist"/>
</hibernate-reverse-engineering>